{"1":"custom-ThinkKmsRope.png","2":"custom-YasunaNiceDesuNe.png","3":"custom-DogGrin.png","4":"custom-TobiasLick.png","5":"custom-FrankWat.png","6":"custom-PepePog4.png","7":"custom-ThinkKmsGun.png","8":"custom-PepeKms.png","9":"custom-PepeRage2.png","10":"custom-AkariBully.png","11":"custom-VampyYay.png","12":"custom-ShallBaka.png","13":"custom-AstolfoSleep.png","14":"custom-AquaCry1.png","15":"custom-AquaCry2.png","16":"custom-AquaYay.png","17":"custom-SawakoWat.png","18":"custom-OchakoCry.png","19":"custom-KohinaKms.png","20":"custom-ChiakiYay.png","21":"custom-ThonkThinkCool.png","22":"custom-AngeryCry.png","23":"custom-MikeyGottem.png","24":"custom-DogAngry.png","25":"custom-TrumpSweat.png","26":"custom-LegacyBlobPing.png","27":"custom-BlobHug.png","28":"custom-LegacyBlobHug.png","29":"custom-AwooGasm.png","30":"custom-ReimuWink.png","31":"custom-CorrinSip.png","32":"custom-PepeAngry.png","33":"custom-ThenkThinkAngry.png","34":"custom-KogasaBlush.png","35":"custom-ThatGuyAngry.png","36":"custom-ThatGuyWave.png","37":"custom-FerretYay.png","38":"custom-NotLikeDuck.png","39":"custom-Bananya.png","40":"custom-PepeThinkSmug.png","41":"custom-ShinobuHappy.png","42":"custom-DogSmug.png","43":"custom-AngeryDisgust.png","44":"custom-NotLikeShall.png","45":"custom-DekomoriSmug.png","46":"custom-EmiliaLurk.png","47":"custom-ChloeWat.png","48":"custom-EyesZoom.png","49":"custom-CaillouDisgust.png","50":"custom-2BBlush.png","51":"custom-GingerThink.png","52":"custom-ThinkWink.png","53":"custom-RengeNyanpasu.png","54":"custom-DvaGrin.png","55":"custom-PenguCry.png","56":"custom-PenguSit.png","57":"custom-PepeCry.png","58":"custom-ThenkThink.png","59":"custom-AwooAngry.png","60":"custom-FeelsCry.png","61":"custom-PepeLifeCry.png","62":"custom-PepeOmegaSweat.png","63":"custom-AwooSmug.png","64":"custom-AwooGrin.png","65":"custom-SpongeAngry.png","66":"custom-ThinkStare.png","67":"custom-EyesAngry.png","68":"custom-PepeSweat2.png","69":"custom-AinsGrin.png","70":"custom-TysonWat.png","71":"custom-HandSlam.png","72":"custom-PepeOmegaRage.png","73":"custom-2BHappy.png","74":"custom-ThonkHypeFastThink.png","75":"custom-PepeCallPolice.png","76":"custom-PepePolice.png","77":"custom-AngeryCry2.png","78":"custom-PepeHug.png","79":"custom-WendySmug.png","80":"custom-MeguAngry.png","81":"custom-DogFat.png","82":"custom-TrumpDisgust.png","83":"custom-PepeReal.png","84":"custom-AwooEvil.png","85":"custom-WendySmug2.png","86":"custom-2BHappy2.png","87":"custom-WidowSmug.png","88":"custom-OkHandFire.png","89":"custom-AwooAngry2.png","90":"custom-BlobHypeSweat.png","91":"custom-ArrowTruYes.png","92":"custom-ArrowNo.png","93":"custom-PepeBan.png","94":"custom-AiGasm.png","95":"custom-AiWat.png","96":"custom-MeguGun.png","97":"custom-ThonkThinkLurk.png","98":"custom-ThonkThinkAngry.png","99":"custom-PepeDJ.png","100":"custom-SlavStop.png","101":"custom-DekuDance.gif","102":"custom-HandPat.png","103":"custom-NozomiSmug.png","104":"custom-NyaThink.png","105":"custom-KannaPoint.png","106":"custom-KannaGlare.png","107":"custom-NotLikeMegu.png","108":"custom-SuperHypeUltraLul.png","109":"custom-SuperHypeUltraOmegaGodLul.png","110":"custom-RokaHug.png","111":"custom-ScrollAngryThrow.png","112":"custom-RaiderDance.gif","113":"custom-RickLurk.png","114":"custom-ChiyaGreenTea.png","115":"custom-KokoaCawfee.png","116":"custom-FeelsHype.png","117":"custom-AwooDance.gif","118":"custom-MauiSmug.png","119":"custom-AquaCry3.png","120":"custom-CatPantsuAngry.gif","121":"custom-PepeYay.png","122":"custom-AwooYay.png","123":"custom-AwooRage.png","124":"custom-AwooOkHand.png","125":"custom-AwooFeelsGood.png","126":"custom-PepePog3.png","127":"custom-NepSmugito.png","128":"custom-ThatGuyShrug.png","129":"custom-DrakeYes.png","130":"custom-VindictusCool.png","131":"custom-GordoWat.png","132":"custom-SteamSalty.png","133":"custom-Only399.png","134":"custom-SpaceDogWeird.png","135":"custom-PepeDance.gif","136":"custom-RemDance.gif","137":"custom-BearHypeDance.gif","138":"custom-KagaPillowNo.png","139":"custom-KagaPillowYes.png","140":"custom-SylvieCheekPat.png","141":"custom-RooDuckYay.gif","142":"custom-HypeFerghus.png","143":"custom-PepePog.png","144":"custom-EmiliaSmh.png","145":"custom-VindictusThumbsUp.png","146":"custom-VindictusLul.png","147":"custom-VindictusSigh.png","148":"custom-HinaRunAway.gif","149":"custom-ThinkSpin.gif","150":"custom-FeelsHappy.png","151":"custom-BlobXD.png","152":"custom-TsukihiDance.gif","153":"custom-RaphiXD.png","154":"custom-CirnoWave.png","155":"custom-CirnoShrug.png","156":"custom-AstolfoSip.png","157":"custom-DrakeNo.png","158":"custom-KannaGun.png","159":"custom-PanSmug.png","160":"custom-AkariDontBully.png","161":"custom-PepeYay2.gif","162":"custom-MiyanoYay.gif","163":"custom-EmojiShrug.png","164":"custom-AwooDance2.gif","165":"custom-KumiAngry.png","166":"custom-KumiWave.png","167":"custom-NotLikeAyano.png","168":"custom-RooThink.png","169":"custom-SansDab.gif","170":"custom-SansDance.gif","171":"custom-BlobDance.gif","172":"custom-PepeCryDJ.png","173":"custom-TableSlam.gif","174":"custom-UsamiKms.png","175":"custom-KumiHeart.png","176":"custom-PipiAngry.png","177":"custom-SpongeBoi.gif","178":"custom-KyoukoHug.png","179":"custom-PepeLul.png","180":"custom-BlobHeart.png","181":"custom-BlobHypePolice.png","182":"custom-BorjaLul.png","183":"custom-RaphiHappy.png","184":"custom-NyaGun.png","185":"custom-ErikaISee.png","186":"custom-PepeYay3.png","187":"custom-FrogHypeRoll.gif","188":"custom-PepeDance2.gif","189":"custom-DevShock.png","190":"custom-AoiDance.gif","191":"custom-CirnoCry.png","192":"custom-CirnoSlainHappy.png","193":"custom-PepeRage.png","194":"custom-SachiHeart.png","195":"custom-TophSmug.png","196":"custom-KumiShock.png","197":"custom-KumiBlush.png","198":"custom-KumiCry.png","199":"custom-MiyanoSlam.gif","200":"custom-CatBamboozled.png","201":"custom-DevAngry.png","202":"custom-DevGlare.png","203":"custom-SpookyDance.gif","204":"custom-HypeEyes.png","205":"custom-OkHandLewd.png","206":"custom-EdupsHAhaa.png","207":"custom-AkaneShrug.png","208":"custom-KrisDance.gif","209":"custom-ThinkHitOrMiss.png","210":"custom-NoraDance.gif","211":"custom-SylvieHeadPat.png","212":"custom-RaphiHappy2.png","213":"custom-PepeRun.gif","214":"custom-HinaRun.gif","215":"custom-ValleLul.png","216":"custom-HinaHypeFastRun.gif","217":"custom-HinaRoll.gif","218":"custom-RainbowDance.gif","219":"custom-SagiriBleh.png","220":"custom-NayuBongoSlam.gif","221":"custom-EmojiCool.png","222":"custom-GuraDance.gif","223":"custom-PepeMegaSweat.png","224":"custom-PepePoliceGun.png","225":"custom-PepeDance3.gif","226":"custom-PepeGun.png","227":"custom-PepeSadHug.png","228":"custom-PepeOkHand.png","229":"custom-PepeHeart.png","230":"custom-PepeWow.png","231":"custom-PepePresent.png","232":"custom-PepeEz.png","233":"custom-ArisuDead.png","234":"custom-BugcatDance.gif","235":"custom-CirnoDab.gif","236":"custom-EmojiGasm.gif","237":"custom-GarfieldDead.png","238":"custom-AnnaLick.gif","239":"custom-KannaDance.gif","240":"custom-PepeFat.png","241":"custom-PepeLifeCry2.png","242":"custom-PepePat.png","243":"custom-PepeCry2.png","244":"custom-PepeShrug.png","245":"custom-PepeSweat.png","246":"custom-PepeWow2.png","247":"custom-PepeYay4.png","248":"custom-PepeWeird.png","249":"custom-PinguXD.png","250":"custom-ShimadaDance.gif","251":"custom-ChomusukeAww.png","252":"custom-ChomusukeHappy.png","253":"custom-DogGrin2.png","254":"custom-MeiCry.png","255":"custom-PepeChrist.png","256":"custom-PepeCry3.png","257":"custom-PepeEvil.png","258":"custom-PepeHappy.png","259":"custom-PepeLurk.png","260":"custom-PepeLurkChrist.png","261":"custom-PepePog2.png","262":"custom-PepeCry.png","263":"custom-PepeSadHug2.png","264":"custom-PepeSalute.png","265":"custom-PepesSweat.png","266":"custom-PepeThink.png","267":"custom-RooWhine.png","268":"custom-MiyanoOk.gif","269":"custom-UgandaWat.png","270":"custom-JojoMenacing.png","271":"custom-Oof.png","272":"custom-NotLikeNuthin.png","273":"custom-BttvShock.png","274":"custom-MockSleep.png","275":"custom-DogCool.gif","276":"custom-KokomiWow.png","277":"custom-PepeDetective.png","278":"custom-NyaDab.png","279":"custom-RizePout.png","280":"custom-MeguHug.png","281":"custom-TwitchLul.png","282":"custom-RumiaDance.gif","283":"custom-JojoDance.gif","284":"custom-HatkidDance.gif","285":"custom-KannaNom.png","286":"custom-BlobGun.png","287":"custom-BlobCatOkHand.png","288":"custom-NyaCry.png","289":"custom-PepeHitOrMiss.png","290":"custom-AyayaHappy.png","291":"custom-DogShock.png","292":"custom-DogSweat.png","293":"custom-KyoukoSmug.png","294":"custom-LoudXD.png","295":"custom-MarisaXD.png","296":"custom-MokouSweat.png","297":"custom-PatchouliBlush.png","298":"custom-RanDisgust.png","299":"custom-ReimuSlam.gif","300":"custom-RemberHappy.png","301":"custom-SeijaLurk.png","302":"custom-TewiBan.png","303":"custom-WanLurk.png","304":"custom-YamameSleep.png","305":"custom-YoumuBlush.png","306":"custom-YukariLurk.png","307":"custom-YukariSmug.png","308":"custom-YuyukoDance.gif","309":"custom-NitoriDance.gif","310":"custom-BlobCatPout.png","311":"custom-LilySleep.png","312":"custom-BlobCatMeltThumbsUp.png","313":"custom-CatKnife.png","314":"custom-BugcatHeart.gif","315":"custom-BugcatHug.png","316":"custom-PikaDab.gif","317":"custom-TohruMuscle.png","318":"custom-TubbsFedora.png","319":"custom-KyokoDance.gif","320":"custom-BirdDance.gif","321":"custom-CharmanderRun.gif","322":"custom-SquirtleCoolWalk.gif","323":"custom-BenderDance.gif","324":"custom-ZoidbergMock.png","325":"custom-LuigiNom.gif","326":"custom-StitchCry.gif","327":"custom-CatCry.png","328":"custom-EmojiBoi.gif","329":"custom-EmojiCryLul.png","330":"custom-EmojiHeart.png","331":"custom-RooSip.png","332":"custom-ThinkFakU.png","333":"custom-ThinkSmugLul.png","334":"custom-TaigaYay.gif","335":"custom-BlobCatRage.png","336":"custom-BugcatKiss.gif","337":"custom-BrainExpand.png","338":"custom-SataniaCry.gif","339":"custom-AkkoShrug.png","340":"custom-BlobCatKnife.png","341":"custom-BlobMuscle.png","342":"custom-BlobNom.png","343":"custom-BlobSadPat.gif","344":"custom-FelixKiss.png","345":"custom-KannaSip.png","346":"custom-KannaWat.png","347":"custom-KappaLul.png","348":"custom-MeguGasm.png","349":"custom-PepeGlare.png","350":"custom-PepeKnife.png","351":"custom-PepePantsuYay.png","352":"custom-PepeUgandaSweat.png","353":"custom-PepeYikes.png","354":"custom-PogChamp.png","355":"custom-PusheenBlob.png","356":"custom-RamKiss.png","357":"custom-RemKiss.png","358":"custom-SagiriBlush.png","359":"custom-ThonkThinkSpin.gif","360":"custom-ZeroTwoSmug.png","361":"custom-AngeryPout.png","362":"custom-HaroldHAhaa.png","363":"custom-PikachuShock.png","364":"custom-ReeceThinkSmart.png","365":"custom-BlobPat.gif","366":"custom-PepeYayBan.png","367":"custom-HackerMan.png","368":"custom-NyaOwo.png","369":"custom-HoloNom.png","370":"custom-MiyanoWow.png","371":"custom-MiyanoHug.png","372":"custom-AwooPout.png","373":"custom-NinoWat.png","374":"custom-ResidentSleeper.png","375":"custom-MiyuPray.png","376":"custom-PepeSmugSit.png","377":"custom-PepeShock.png","378":"custom-UnoReverse.png","379":"custom-BugcatCry.gif","380":"custom-BugcatKissNom.gif","381":"custom-Sad4Head.png","382":"custom-NanaDJ.png","383":"custom-KagamiSigh.png","384":"custom-ThatGuyCry.png","385":"custom-WooperHappy.png","386":"custom-AkkoAngry.png","387":"custom-AkkoHug.png","388":"custom-AkkoBlush.png","389":"custom-AkkoSweat.png","390":"custom-AkkoWave.png","391":"custom-EmojiYeeHawCry.png","392":"custom-KannaShock.png","393":"custom-KannaOut.png","394":"custom-KannaOut2.png","395":"custom-KannaWow.png","396":"custom-NyaBlush.png","397":"custom-NyaPresent.png","398":"custom-ThatGuyCry.png","399":"custom-ThatGuyHappy.png","400":"custom-ThatGuyShock.png","401":"custom-SayoriDead.png","402":"custom-NanaRun.png","403":"custom-ChikaXD.gif","404":"custom-CrashWeird.png","405":"custom-EyesPog.png","406":"custom-BlobDJ.gif","407":"custom-Pepega.png","408":"custom-KirbyDJ.gif","409":"custom-RamDisgust.png","410":"custom-MaiSmug.png","411":"custom-HinaSlam.gif","412":"custom-EdupsDisrespect.png","413":"custom-NotLikeMaho.png","414":"custom-ChikaDance.gif","415":"custom-ChikaDance2.gif","416":"custom-ChikaSpin.gif","417":"custom-ChikaSpin2.gif","418":"custom-ChikaDJ.gif","419":"custom-AkariThink.png","420":"custom-LuxLurk.png","421":"custom-HideriGlare.png","422":"custom-DogDance.gif","423":"custom-LinkYay.gif","424":"custom-OrangeKidDance.gif","425":"custom-ZuraXD.png","426":"custom-SataniaXD.png","427":"custom-HometeXD.png","428":"custom-KokoroYay.png","429":"custom-SataniaBox.png","430":"custom-EarlRun.gif","431":"custom-PoiNomXD.png","432":"custom-PepeSaluteCry.png","433":"custom-EmojiKms.gif","434":"custom-PepeClap.gif","435":"custom-PepeGasm.png","436":"custom-PepeHug2.png","437":"custom-SataniaBlush.png","438":"custom-DogWeird.png","439":"custom-NanaLurk.png","440":"custom-BlobCatDab.gif","441":"custom-RooBlush.png","442":"custom-BlobHappy.png","443":"custom-AiSmug.png","444":"custom-FoxWow.png","445":"custom-MeguDead.png","446":"custom-MeguWat.png","447":"custom-RemPout.png","448":"custom-SataniaShock.png","449":"custom-UmaruCry.png","450":"custom-ChikaDance3.gif","451":"custom-RooAww.png","452":"custom-PepeSweatGrin.png","453":"custom-PepeCryHappyDJ.png","454":"custom-ChikaAyayaHappy.png","455":"custom-UmaruCool.png","456":"custom-HinaSleep.png","457":"custom-PepeSadSit.png","458":"custom-WheezerGasm.png","459":"custom-NotLikeBlobCry.png","460":"custom-AstolfoSleepHype.png","461":"custom-AstolfoSleepUltraHype.png","462":"custom-PepeCryMask.png","463":"custom-BelDance.gif","464":"custom-KannaDetective.png","465":"custom-KannaCry.gif","466":"custom-BlobDanceNom.gif","467":"custom-FelixCool.png","468":"custom-KaguyaNom.png","469":"custom-WeissHeart.png","470":"custom-AyaHappy.png","471":"custom-EvePray.png","472":"custom-RooPray.png","473":"custom-AniDab.png","474":"custom-PixenSlide.gif","475":"custom-NoelYay.png","476":"custom-BlobGhostHug.png","477":"custom-ThatGuyNoPingHappy.png","478":"custom-BipComfySleep.png","479":"custom-PeachyWiggle.gif","480":"custom-YukinaJumpYay.gif","481":"custom-EggplantVeins.png","482":"custom-EmojiPlushCryLul.png","483":"custom-RainbowSheepSpin.gif","484":"custom-ArisaDead.png","485":"custom-SadChamp.png","486":"custom-IbukiPadoru.png","487":"custom-WeirdChamp.png","488":"custom-PepegaDance.gif","489":"custom-NagatoroDisgust.png","490":"custom-NagatoroDisgust2.png","491":"custom-NagatoroHappy.png","492":"custom-NagatoroShock.png","493":"custom-NagatoroSmug.png","494":"custom-NagatoroSmug2.png","495":"custom-NagatoroSmug3.png","496":"custom-NagatoroWave.png","497":"custom-NagatoroLul.png","498":"custom-NagatoroLulXD.png","499":"custom-NagatoroSmug4.png","500":"custom-NagatoroShock2.png","501":"custom-NagatoroNoDisgust.png","502":"custom-NagatoroRun.png","503":"custom-NagatoroShrug.png","504":"custom-NagatoroDead.png","505":"custom-NagatoroShock3.png","506":"custom-NagatoroNom.png","507":"custom-BabyTaikoDrum.png","508":"custom-FelixThink.png","509":"custom-CleaCry.png","510":"custom-OsuHow.png","511":"custom-YukikoHappy.png","512":"custom-NoelWave.png","513":"custom-NoelSleep.png","514":"custom-NoelCry.png","515":"custom-NoelGasm.png","516":"custom-BoatThink.png","517":"custom-HackerPepeCool.gif","518":"custom-DioRareDance.gif","519":"custom-AwooMenacing.png","520":"custom-YoshiRipple.gif","521":"custom-YoshiRippleSmall.gif","522":"custom-ThompsonShockChrist.gif","523":"custom-DioPepeRage.png","524":"custom-ObamaOrbSpin.gif","525":"custom-Brain4Head.png","526":"custom-CoolChamp.png","527":"custom-DansGameHype.png","528":"custom-GachiGasmYay.png","529":"custom-KappaLurk.png","530":"custom-OmegaLul.png","531":"custom-OkayChamp.png","532":"custom-PepePogStupid.png","533":"custom-PainsChamp.png","534":"custom-PauseChamp.png","535":"custom-PointChamp.png","536":"custom-PogChampNom.png","537":"custom-StareChamp.png","538":"custom-NagatoroGlare.png","539":"custom-OkHandDrops.png","540":"custom-CirnoDisgust.png","541":"custom-HattereneSmug.png","542":"custom-CantaOwo.png","543":"custom-NagatoroDead2.png","544":"custom-NagatoroDisgust3.png","545":"custom-NagatoroDisgust4.png","546":"custom-NagatoroGlare2.png","547":"custom-NagatoroGlare3.png","548":"custom-NagatoroPoint.png","549":"custom-NagatoroPray.png","550":"custom-NagatoroSalute.png","551":"custom-NagatoroSmug5.png","552":"custom-NagatoroThinkSmart.png","553":"custom-NagatoroThumbsUp.png","554":"custom-NagatoroWow.png","555":"custom-FangirlFeels.png","556":"custom-FangirlNom.png","557":"custom-FangirlNotLikeThisCry.png","558":"custom-FangirlShock.png","559":"custom-FangirlShrug.png","560":"custom-FangirlWat.png","561":"custom-AkkoAngry2.png","562":"custom-AkkoDead.png","563":"custom-AkkoPout.png","564":"custom-AkkoPout2.png","565":"custom-AkkoRage.png","566":"custom-AkkoCry.png","567":"custom-AkkoSleep.png","568":"custom-AkkoSmug.png","569":"custom-AkkoThink.png","570":"custom-AkkoWat.png","571":"custom-AkkoWeird.png","572":"custom-AkkoWow.png","573":"custom-AkkoYay.png","574":"custom-GachiGasmHype.png","575":"custom-BttvClap.gif","576":"custom-Zulul.png","577":"custom-PepeOld.png","578":"custom-GirlSlam.gif","579":"custom-AkkoHug2.png","580":"custom-MeguLurk.png","581":"custom-NoelPat.png","582":"custom-OsuNoU.png","583":"custom-NotLikeEmojiCryLul.png","584":"custom-ObamaPrismSpin.gif","585":"custom-PepeNoUYay.gif","586":"custom-OsuWho.png","587":"custom-HachuAngry.png","588":"custom-IdkeStare.png","589":"custom-PepegaLifeCry.png","590":"custom-TriHardConnect.gif","591":"custom-TwitchHappyStare.png","592":"custom-NotLikeTerada.png","593":"custom-TeradaAngry.png","594":"custom-TeradaClap.png","595":"custom-TeradaCool.png","596":"custom-TeradaCry.png","597":"custom-TeradaDeadGlare.png","598":"custom-TeradaDisgust.png","599":"custom-TeradaDisgust2.png","600":"custom-TeradaDJ.png","601":"custom-TeradaEvil.png","602":"custom-TeradaFacepalm.png","603":"custom-TeradaBlush.png","604":"custom-TeradaBlush2.png","605":"custom-TeradaBlush3.png","606":"custom-TeradaOkHand.png","607":"custom-TeradaPointSmug.png","608":"custom-TeradaPout.png","609":"custom-TeradaPray.png","610":"custom-TeradaSalute.png","611":"custom-TeradaShock.png","612":"custom-TeradaShock2.png","613":"custom-TeradaShock3.png","614":"custom-TeradaShock4.png","615":"custom-TeradaShock5.png","616":"custom-TeradaSleep.png","617":"custom-TeradaSleep2.png","618":"custom-TeradaSleep3.png","619":"custom-TeradaSmug.png","620":"custom-TeradaSmug2.png","621":"custom-TeradaSmug3.png","622":"custom-TeradaThumbsDown.png","623":"custom-TeradaWat.png","624":"custom-TeradaWeird.png","625":"custom-TeradaYay.png","626":"custom-FurretHeartHug.png","627":"custom-ThompsonSlam.gif","628":"custom-VeronicaSip.png","629":"custom-HamijoDance.gif","630":"custom-KarthySmug.png","631":"custom-KarthyWeird.png","632":"custom-KarthyDisgust.png","633":"custom-KarthyHappy.png","634":"custom-BerdDance.gif","635":"custom-BongoHeart.gif","636":"custom-FroppyPingAngry.png","637":"custom-NagatoroSmug6.png","638":"custom-SandyRun.gif","639":"custom-NanaCry.png","640":"custom-NanaSorry.png","641":"custom-NanaISee.png","642":"custom-NanaSleep.png","643":"custom-FirekeeperPantsuBlush.png","644":"custom-FirekeeperPantsuHappy.png","645":"custom-FirekeeperPantsuHeart.png","646":"custom-GwyndolinShock.png","647":"custom-HikariSlam.gif","648":"custom-02Shrug.png","649":"custom-KanaoRun.gif","650":"custom-NezukoRun.gif","651":"custom-RabbitDance.gif","652":"custom-BlobCry.png","653":"custom-MikuShock.png","654":"custom-MikuShrug.png","655":"custom-VindictusEyes.png","656":"custom-VindictusCry.png","657":"custom-VindictusYes.png","658":"custom-VindictusNo.png","659":"custom-VindictusWave.png","660":"custom-LavenderSlam.gif","661":"custom-ShanaSip.png","662":"custom-OtomeLick.gif","663":"custom-ShinobuPat.gif","664":"custom-ShanaHeart.png","665":"custom-K3llyAngry.png","666":"custom-K3llyAww.png","667":"custom-K3llyDead.png","668":"custom-K3llyHug.png","669":"custom-K3llyPat.png","670":"custom-K3llyThink.png","671":"custom-K3llyNom.gif","672":"custom-ShanaNom.png","673":"custom-ZeroTwoDead.png","674":"custom-RamPoint.png","675":"custom-EmojiGasmKnife.png","676":"custom-PikachuDance.gif","677":"custom-JojoDance2.gif","678":"custom-MultiYay.gif","679":"custom-KannaFacepalm.png","680":"custom-BunbunSmug.png","681":"custom-PepeDJSit.gif","682":"custom-JalterPout.png","683":"custom-KannaFU.png","684":"custom-HornetDance.gif","685":"custom-HornetDance2.gif","686":"custom-KnightDance.gif","687":"custom-SnomDance.gif","688":"custom-SprioleHappy.png","689":"custom-PepeSweatMaskSoap.gif","690":"custom-LyriaOkBoomer.png","691":"custom-PriscillaAngry.png","692":"custom-PriscillaRage.png","693":"custom-SylvieHeadPat2.png","694":"custom-PepePogChamp.png","695":"custom-DogPray.png","696":"custom-BlobBlush.png","697":"custom-PepeLul2.gif","698":"custom-EmojiCoolSmug.png","699":"custom-ChickenCry.png","700":"custom-MigmigCry.png","701":"custom-MigmigHeart.png","702":"custom-MigmigHappyLul.png","703":"custom-MigmigLurk.png","704":"custom-MigmigSleep.png","705":"custom-EmojiBlushBloat.png","706":"custom-PatrickGasm.png","707":"custom-NoUNeon.gif","708":"custom-KannaCool.png","709":"custom-FrostleafOk.png","710":"custom-FrostleafFacepalm.png","711":"custom-FrostleafSmug.png","712":"custom-FrostleafNom.png","713":"custom-FrostleafSmug2.png","714":"custom-FrostleafWat.png","715":"custom-K3llyPray.png","716":"custom-K3llyAngry2.png","717":"custom-K3llyAngry3.png","718":"custom-K3llyBaka.png","719":"custom-K3llyBlush.png","720":"custom-K3llyBlush2.png","721":"custom-K3llyCry.png","722":"custom-K3llyCry2.png","723":"custom-K3llyCry3.png","724":"custom-K3llyCry4.png","725":"custom-K3llyDance.png","726":"custom-K3llyWow.png","727":"custom-K3llyEvil.png","728":"custom-K3llyHeart.png","729":"custom-K3llyHeart2.png","730":"custom-K3llyHug2.png","731":"custom-K3llyHug3.png","732":"custom-K3llyGlare.png","733":"custom-K3llyLul.png","734":"custom-K3llyLul2.png","735":"custom-K3llyWink.png","736":"custom-K3llyPoutTongue.png","737":"custom-K3llyNo.png","738":"custom-K3llyNom2.png","739":"custom-K3llyOkHand.png","740":"custom-K3llyOwo.png","741":"custom-K3llyPat2.png","742":"custom-K3llyLurk.png","743":"custom-K3llyLurk2.png","744":"custom-K3llyLurk3.png","745":"custom-K3llyPolice.png","746":"custom-K3llyPout.png","747":"custom-K3llyCry5.png","748":"custom-K3llySalute.png","749":"custom-K3llyShock.png","750":"custom-K3llySip.png","751":"custom-K3llyDJSip.png","752":"custom-K3llySleep.png","753":"custom-K3llySleep2.png","754":"custom-K3llySleep3.png","755":"custom-K3llyStache.png","756":"custom-K3llyThink2.png","757":"custom-K3llyThink3.png","758":"custom-K3llyThumbsUp.png","759":"custom-K3llyWat.png","760":"custom-HideriMelt.png","761":"custom-KoroneDance.gif","762":"custom-DogDance2.gif","763":"custom-CirnoPat.png","764":"custom-CatSad2.png","765":"custom-CatCry.png","766":"custom-NagatoroHandHold.png","767":"custom-KaguyaShrug.png","768":"custom-DogPray2.png","769":"custom-KumiCry2.png","770":"custom-KumiNom.png","771":"custom-KumiNom2.png","772":"custom-KumiXD.png","773":"custom-KumiYay.png","774":"custom-LisaWat.png","775":"custom-KoroneNo.png","776":"custom-KoroneDance2.gif","777":"custom-HelltakerThink.png","778":"custom-HelltakerSip.png","779":"custom-HelltakerPog.png","780":"custom-HelltakerSweat.png","781":"custom-HelltakerGasm.png","782":"custom-HelltakerSweatEyes.png","783":"custom-HelltakerSweatEyes2.png","784":"custom-HelltakerSmug.png","785":"custom-HelltakerBlush.png","786":"custom-HelltakerDead.png","787":"custom-HelltakerStare.png","788":"custom-GlowwormISee.png","789":"custom-HelltakerDance.gif","790":"custom-HelltakerDance2.gif","791":"custom-RoachHoesMad.gif","792":"custom-HibikiThumbsUp.png","793":"custom-KoroneDance3.gif","794":"custom-NeroPadoruCry.png","795":"custom-CatDance.gif","796":"custom-FlanXD.png","797":"custom-PepeWeird2.png","798":"custom-EmojiSadDead.png","799":"custom-FumizukiChrist.png","800":"custom-PepeHype.png","801":"custom-NotLikePepe.png","802":"custom-KoroneDance4.gif","803":"custom-AnnaHappy.png","804":"custom-AnnaCry.png","805":"custom-AnnaThink.png","806":"custom-02Gasm.png","807":"custom-PogChamp2.gif","808":"custom-ShinanoDance.gif","809":"custom-ShinanoHappy.png","810":"custom-WooYeahDance.gif","811":"custom-K3llyAngry4.png","812":"custom-K3llyBlush3.png","813":"custom-K3llyCatWat.png","814":"custom-K3llySip2.png","815":"custom-K3llyComfy.png","816":"custom-K3llyDead2.png","817":"custom-K3llyGlare2.png","818":"custom-K3llyHeart3.png","819":"custom-NotLikeK3lly.png","820":"custom-K3llyNom3.png","821":"custom-K3llyOut.png","822":"custom-K3llyWave.png","823":"custom-K3llyPenYay.png","824":"custom-K3llyPolice2.png","825":"custom-K3llyPray2.png","826":"custom-K3llyShock2.png","827":"custom-K3llySmart.png","828":"custom-K3llySmug.png","829":"custom-PaimonAngry.png","830":"custom-PaimonCry.png","831":"custom-PaimonShock.png","832":"custom-PaimonThink.png","833":"custom-AmberRage.png","834":"custom-LisaHappy.png","835":"custom-PaimonKnife.png","836":"custom-PaimonClap.gif","837":"custom-NingguangHappy.png","838":"custom-PaimonSmug.png","839":"custom-KeqingHeart.png","840":"custom-KleeCry.png","841":"custom-KleeGasm.png","842":"custom-KleeHug.png","843":"custom-QiqiShock.png","844":"custom-XianglingWow.png","845":"custom-QiqiISee.png","846":"custom-KagaAkagiHug.png","847":"custom-AmberHug.png","848":"custom-KleeYay.png","849":"custom-LisaBlushSmug.png","850":"custom-PaimonDead.png","851":"custom-PaimonPout.png","852":"custom-PaimonSmug2.png","853":"custom-QiqiThinkWat.png","854":"custom-SucrosePray.png","855":"custom-PepeSad2.png","856":"custom-LumineWalk.gif","857":"custom-PaimonNom.gif","858":"custom-AmberPog.png","859":"custom-LisaSleep.png","860":"custom-NingguangAngry.png","861":"custom-PaimonThink2.png","862":"custom-XianglingNom.png","863":"custom-EmojiNodYes.gif","864":"custom-EssexNodYes.gif","865":"custom-NeptuneNodYes.gif","866":"custom-HazeThink.png","867":"custom-InitialDRunDrift.gif","868":"custom-TelepeturtlePat.gif","869":"custom-PepeDisgust.png","870":"custom-PepeCry4.png","871":"custom-EmiliaAngry.png","872":"custom-EmojiEyes.png","873":"custom-WatameNod.gif","874":"custom-PurpleDoveDance.gif","875":"custom-Brain2Head.png","876":"custom-FPayRespectCry.png","877":"custom-GavinWeird.png","878":"custom-PlateletBan.png","879":"custom-NoU.gif","880":"custom-LurkPing.gif","881":"custom-ClownAward.png","882":"custom-Minus1.png","883":"custom-Plus1.png","884":"custom-NoelDab.png","885":"custom-PekoraDance.gif","886":"custom-PepeSweat3.gif","887":"custom-QiqiShrug.png","888":"custom-HollowDJ.png","889":"custom-1_.gif","890":"custom-2_.gif","891":"custom-3_.gif","892":"custom-4_.gif","893":"custom-5_.gif","894":"custom-6_.gif","895":"custom-aBronyaStare.gif","896":"custom-AceFeels.gif","897":"custom-aFuHuaSaltBabe.gif","898":"custom-aFuHuaWicked.gif","899":"custom-aHigoPing.gif","900":"custom-aHimekoKiss.gif","901":"custom-aHimekoWTF.gif","902":"custom-aHoVLoading.gif","903":"custom-AichanBlink.gif","904":"custom-AichanBlush.gif","905":"custom-AichanCry.gif","906":"custom-AichanError.gif","907":"custom-AichanLaugh.gif","908":"custom-AichanSorry.gif","909":"custom-AichanWave.gif","910":"custom-AichanWhale.gif","911":"custom-aJahySadLeave.gif","912":"custom-aKianaBat.gif","913":"custom-aKianaDumb.gif","914":"custom-aKianaSmug.gif","915":"custom-aKurikaraWhat.gif","916":"custom-Alpha_annoyed.gif","917":"custom-angryHype.gif","918":"custom-animebonk.gif","919":"custom-animeHELLAexcited.gif","920":"custom-animehug.gif","921":"custom-animekiss.gif","922":"custom-ApooJam.gif","923":"custom-Approved.gif","924":"custom-aSeeleSweat.gif","925":"custom-aTeriChrist.gif","926":"custom-aTeriSmug.gif","927":"custom-aTeriSparkle.gif","928":"custom-awyeah.gif","929":"custom-BaalCry_2.gif","930":"custom-Baal_writing.gif","931":"custom-BanThem.gif","932":"custom-baronbunnydance.gif","933":"custom-BellaLove.gif","934":"custom-BellaPat.gif","935":"custom-BellaPout.gif","936":"custom-BellaSorry.gif","937":"custom-BenaresTransform.gif","938":"custom-BiccSeeleIntensifies.gif","939":"custom-blinkwhat.gif","940":"custom-blobhype.gif","941":"custom-BobbinDance.gif","942":"custom-Botan_smug.gif","943":"custom-BronyaAlone.gif","944":"custom-BronyaChill.gif","945":"custom-BronyaDance.gif","946":"custom-BronyaJump.gif","947":"custom-BrookRun.gif","948":"custom-BrookSip.gif","949":"custom-BrookSmoke.gif","950":"custom-BuggyMcD.gif","951":"custom-Burn.gif","952":"custom-CaesarHuh.gif","953":"custom-caramelldansen.gif","954":"custom-CarooNOO.gif","955":"custom-CarrotSmile.gif","956":"custom-CarrotYes.gif","957":"custom-catbonk.gif","958":"custom-catcry.gif","959":"custom-catmeetskeyboard.gif","960":"custom-checkpin.gif","961":"custom-ChopperPet.gif","962":"custom-CobySalute.gif","963":"custom-Compote.gif","964":"custom-CrocNo.gif","965":"custom-CrocoBonk.gif","966":"custom-CryKayo.gif","967":"custom-CryMeARiver.gif","968":"custom-CuteBongoYATTA.gif","969":"custom-cute_pat.gif","970":"custom-dancindoggo.gif","971":"custom-DancingQueen.gif","972":"custom-DarkChopper.gif","973":"custom-DarkFranky.gif","974":"custom-DarkRobin.gif","975":"custom-DarkSanji.gif","976":"custom-DarkUsopp.gif","977":"custom-DarkZoro.gif","978":"custom-DeltaSlam.gif","979":"custom-doggo_triggered.gif","980":"custom-DONUTROLL.gif","981":"custom-dragon_pat.gif","982":"custom-DurandalGooseL.gif","983":"custom-DurandalGooseR.gif","984":"custom-DurandalMunch.gif","985":"custom-eeveeheart.gif","986":"custom-Elysia_luv_wink.gif","987":"custom-emoji_53.gif","988":"custom-EnelJustShocking.gif","989":"custom-EvilHattori.gif","990":"custom-flip_cat.gif","991":"custom-FrankySunny1.gif","992":"custom-FrankySunny2.gif","993":"custom-FuHuaAngry.gif","994":"custom-FuHuaEyes.gif","995":"custom-fuhuamunch.gif","996":"custom-FuHuaOra.gif","997":"custom-FujiKOREA.gif","998":"custom-FujiMount.gif","999":"custom-FujiWut.gif","1000":"custom-GaimonOk.gif","1001":"custom-gillaugh.gif","1002":"custom-GoingMerry.gif","1003":"custom-gura_slide.gif","1004":"custom-headpat.gif","1005":"custom-headsmash.gif","1006":"custom-heart_fart.gif","1007":"custom-HigoLurkPing.gif","1008":"custom-HimekoCheers.gif","1009":"custom-HimekoMunch.gif","1010":"custom-homerhide.gif","1011":"custom-HoRMunch.gif","1012":"custom-HoroGasp.gif","1013":"custom-HoSAngery.gif","1014":"custom-HoSBonk.gif","1015":"custom-HoSMunch.gif","1016":"custom-HoS_dancy.gif","1017":"custom-HoTAngry.gif","1018":"custom-HoTBoardFlip.gif","1019":"custom-HoTFetch.gif","1020":"custom-HoTMunch.gif","1021":"custom-HoTTakeoff.gif","1022":"custom-HoTTransform.gif","1023":"custom-HoVUlt.gif","1024":"custom-HOV_dance.gif","1025":"custom-hype.gif","1026":"custom-jahypat.gif","1027":"custom-JinbePet.gif","1028":"custom-KallenMunch.gif","1029":"custom-KallenPopcorn.gif","1030":"custom-KallenShoot.gif","1031":"custom-KallenSleep.gif","1032":"custom-KallenSnore.gif","1033":"custom-KallenSpin.gif","1034":"custom-KataCozyPet.gif","1035":"custom-kekgif.gif","1036":"custom-KianaChickenNom.gif","1037":"custom-KianaCookie.gif","1038":"custom-KianaCookie2.gif","1039":"custom-KianaCooking1.gif","1040":"custom-KianaCooking2.gif","1041":"custom-KianaFlop.gif","1042":"custom-kianahungry.gif","1043":"custom-KianaMunch.gif","1044":"custom-KianaNo.gif","1045":"custom-KianaPing.gif","1046":"custom-KianaPing2.gif","1047":"custom-KianaCry.gif","1048":"custom-KianaShake.gif","1049":"custom-KianaShamashL.gif","1050":"custom-KianaShamashR.gif","1051":"custom-KianaSpin2Win.gif","1052":"custom-KianaStomp.gif","1053":"custom-KianaUwah.gif","1054":"custom-KianaWaiting.gif","1055":"custom-KianaWant.gif","1056":"custom-kianawave.gif","1057":"custom-KickL.gif","1058":"custom-KickM.gif","1059":"custom-KickR.gif","1060":"custom-kirbyparty.gif","1061":"custom-Kirby_rave.gif","1062":"custom-KleeREEEE.gif","1063":"custom-Kobayashi_Clean.gif","1064":"custom-KurikaraArrival.gif","1065":"custom-KurikaraPat.gif","1066":"custom-KurikaraSleep.gif","1067":"custom-KurikaraTakeoff.gif","1068":"custom-LaffeyThumb.gif","1069":"custom-LaffeyThumpsUp.gif","1070":"custom-laughcackle.gif","1071":"custom-LawRoom.gif","1072":"custom-letmein.gif","1073":"custom-lewdstare.gif","1074":"custom-LewdStare2.gif","1075":"custom-licclapp.gif","1076":"custom-LiliLili.gif","1077":"custom-LiliMunch.gif","1078":"custom-Logo.gif","1079":"custom-LuffyDab.gif","1080":"custom-LuffyLaugh.gif","1081":"custom-LuffyNoChapter.gif","1082":"custom-LuffyNonono.gif","1083":"custom-LuffyThonk.gif","1084":"custom-LuffyVv.gif","1085":"custom-LumiLick.gif","1086":"custom-MagellanPoop.gif","1087":"custom-mancry.gif","1088":"custom-MeiCooking.gif","1089":"custom-MeiCurious.gif","1090":"custom-MeiDealWithIt.gif","1091":"custom-MeiKnife.gif","1092":"custom-MeiSob.gif","1093":"custom-MeiTransform.gif","1094":"custom-MeiTunaSlash.gif","1095":"custom-meiwat.gif","1096":"custom-MeiWave.gif","1097":"custom-mindblown.gif","1098":"custom-mona.gif","1099":"custom-mudcatching.gif","1100":"custom-nagahappy.gif","1101":"custom-nekodance.gif","1102":"custom-nekosalute.gif","1103":"custom-NekoStomp.gif","1104":"custom-nervousdoggo.gif","1105":"custom-NimiPing.gif","1106":"custom-NJsmile.gif","1107":"custom-Oduh.gif","1108":"custom-okay.gif","1109":"custom-OrochiDance.gif","1110":"custom-OrochiLaugh.gif","1111":"custom-Owogashima.gif","1112":"custom-Owogifima.gif","1113":"custom-paimonLurk.gif","1114":"custom-paimonprimogems.gif","1115":"custom-pepecryrun.gif","1116":"custom-pepeLS.gif","1117":"custom-pepeohshit.gif","1118":"custom-pepeshy.gif","1119":"custom-PeronaChomp.gif","1120":"custom-PeronaSHOCK.gif","1121":"custom-Perorin.gif","1122":"custom-Punishment_whip.gif","1123":"custom-QuantumBall.gif","1124":"custom-QueenBooba.gif","1125":"custom-QueenShock.gif","1126":"custom-ratREEEEE.gif","1127":"custom-ratshake.gif","1128":"custom-Rattster_rub.gif","1129":"custom-Reimu_tea.gif","1130":"custom-RitaFly.gif","1131":"custom-RitaMunch.gif","1132":"custom-RitaPlaying.gif","1133":"custom-RitaSweep.gif","1134":"custom-RitaWoosh.gif","1135":"custom-RozaFiteMe.gif","1136":"custom-RozaMunch.gif","1137":"custom-RozaOopsPat.gif","1138":"custom-RozaRoza.gif","1139":"custom-run.gif","1140":"custom-SadCat.gif","1141":"custom-SakuraFoxy.gif","1142":"custom-SakuraHigoSpank.gif","1143":"custom-SakuraMacarena.gif","1144":"custom-SakuraMunch.gif","1145":"custom-SakuraNani.gif","1146":"custom-SakuraNom.gif","1147":"custom-SakuraLurk.gif","1148":"custom-SakuraSip.gif","1149":"custom-SakuraSlash.gif","1150":"custom-SakuraSpin.gif","1151":"custom-SakuraYay.gif","1152":"custom-SakuraYes.gif","1153":"custom-Sanji4kids.gif","1154":"custom-SanjiGasp.gif","1155":"custom-SchroWave.gif","1156":"custom-SeeleHuh.gif","1157":"custom-SeeleLook.gif","1158":"custom-SeeleMunch.gif","1159":"custom-SeeleNoted.gif","1160":"custom-seelepat.gif","1161":"custom-SeelePet.gif","1162":"custom-SeeleWha.gif","1163":"custom-SengokuHmm.gif","1164":"custom-shawburst.gif","1165":"custom-shubaduck.gif","1166":"custom-SirinRave.gif","1167":"custom-SmoothieWine.gif","1168":"custom-smug.gif","1169":"custom-SoraHuh.gif","1170":"custom-SoraLost.gif","1171":"custom-SoraSpeechless.gif","1172":"custom-SpeedReader.gif","1173":"custom-SpongebobBOOOIIII.gif","1174":"custom-Spooky_dance.gif","1175":"custom-StrawSkull.gif","1176":"custom-TamaInvestigate.gif","1177":"custom-TeriBully.gif","1178":"custom-TeriDance.gif","1179":"custom-TeriExcite.gif","1180":"custom-TeriFlood.gif","1181":"custom-TeriHypePat.gif","1182":"custom-TeriMelon.gif","1183":"custom-TeriMunch.gif","1184":"custom-TeriPat.gif","1185":"custom-TeriPats.gif","1186":"custom-TeriPraise.gif","1187":"custom-TeRiRiLove.gif","1188":"custom-TeRiRiPersuasion.gif","1189":"custom-TeRiRiPunish.gif","1190":"custom-TeriScare.gif","1191":"custom-TeriSmash.gif","1192":"custom-TeriSmug.gif","1193":"custom-TeriTNT.gif","1194":"custom-TherestheG.gif","1195":"custom-Titan_FckU.gif","1196":"custom-toadAAAAAAAA.gif","1197":"custom-TokoRun.gif","1198":"custom-TuTu.gif","1199":"custom-ultra_autism.gif","1200":"custom-UsoKiss.gif","1201":"custom-VeliAnnoyed.gif","1202":"custom-VeliBlush.gif","1203":"custom-VeliCrush.gif","1204":"custom-VeliEvil.gif","1205":"custom-VeliGlad.gif","1206":"custom-VelionaLove.gif","1207":"custom-VeliSmh.gif","1208":"custom-VeliSparkle.gif","1209":"custom-VeliSweat.gif","1210":"custom-VeliTehe.gif","1211":"custom-VeliTired.gif","1212":"custom-vibincat.gif","1213":"custom-vibinkirby.gif","1214":"custom-ViviPet.gif","1215":"custom-VodkaBonk.gif","1216":"custom-WapolGrab.gif","1217":"custom-watchtheworldburn.gif","1218":"custom-wave.gif","1219":"custom-welcome.gif","1220":"custom-welcome2.gif","1221":"custom-whoasked.gif","1222":"custom-Widebe1.gif","1223":"custom-Widebe3.gif","1224":"custom-Widebei2.gif","1225":"custom-XD.gif","1226":"custom-YallNeedJudah.gif","1227":"custom-YallNeedPledge.gif","1228":"custom-YamaNod.gif","1229":"custom-YATTA_dance.gif","1230":"custom-YATTA_reeeeee.gif","1231":"custom-YATTA_spin.gif","1232":"custom-ZeroTwo.gif","1233":"custom-zerotwocrackjump.gif","1234":"custom-ZeusDed.gif","1235":"custom-ZhugeDance.gif","1236":"custom-ZhugeDance1.gif","1237":"custom-ZhugeDance2.gif","1238":"custom-ZhugeDancePensive.gif","1239":"custom-ZhugeHandFan.gif","1240":"custom-ZhugeLongFan.gif","1241":"custom-ZhugeLongming.gif","1242":"custom-ZoroHUH.gif","1243":"custom-ZoroSmile.gif","1244":"custom-100PercentTrap.png","1245":"custom-320.png","1246":"custom-330.png","1247":"custom-5Foxy.png","1248":"custom-AceJustRight.png","1249":"custom-AegirAra.png","1250":"custom-ahhh.png","1251":"custom-AichanAngery.png","1252":"custom-AichanCool.png","1253":"custom-AichanCrystals.png","1254":"custom-AichanStare.png","1255":"custom-aichanyay.png","1256":"custom-AkagaHug.png","1257":"custom-AkainuLUL.png","1258":"custom-AkainuLULW.png","1259":"custom-AkainuPoint.png","1260":"custom-AkainuSweat.png","1261":"custom-akasmug.png","1262":"custom-AKcoin.png","1263":"custom-Akkainu.png","1264":"custom-ALcube.png","1265":"custom-AmagiLuv.png","1266":"custom-amogus.png","1267":"custom-AngryCat.png","1268":"custom-AnnaPleaseK.png","1269":"custom-ApooHmm.png","1270":"custom-ApooPoint.png","1271":"custom-Aquaheh.png","1272":"custom-Azdaha_derp.png","1273":"custom-BaalCry.png","1274":"custom-Baguttebewithyou.png","1275":"custom-baka.png","1276":"custom-baka_blush_baka2.png","1277":"custom-ban.png","1278":"custom-BBPieSmile.png","1279":"custom-BBRofl.png","1280":"custom-BBZehahaha.png","1281":"custom-BegeTired.png","1282":"custom-BenaresHungry.png","1283":"custom-BennGun.png","1284":"custom-BEPat.png","1285":"custom-BepoBlush.png","1286":"custom-BepoCry.png","1287":"custom-BepoThink.png","1288":"custom-BigNews.png","1289":"custom-bitchplease.png","1290":"custom-BlackCard.png","1291":"custom-BlackCat.png","1292":"custom-blush.png","1293":"custom-blushcat.png","1294":"custom-blushies.png","1295":"custom-blushmega.png","1296":"custom-blushstare.png","1297":"custom-BmWut.png","1298":"custom-BoaBlush.png","1299":"custom-BobbinFeels.png","1300":"custom-BonUp.png","1301":"custom-BronyaCool.png","1302":"custom-BronyaCrystals.png","1303":"custom-BronyaDrink.png","1304":"custom-BronyaFlex.png","1305":"custom-BronyaLurk.png","1306":"custom-BronyaCry.png","1307":"custom-BronyaStare.png","1308":"custom-BronyaTease.png","1309":"custom-BronyaThink.png","1310":"custom-Brookeking.png","1311":"custom-BrookShrug.png","1312":"custom-BrookTea.png","1313":"custom-BuggyHAA.png","1314":"custom-BuggyMonkaS.png","1315":"custom-BuggySweat.png","1316":"custom-CarrotSmug.png","1317":"custom-CarrotYikes.png","1318":"custom-Carueknife.png","1319":"custom-CarueSalute.png","1320":"custom-catbaguettebonk.png","1321":"custom-catcool.png","1322":"custom-catcry.png","1323":"custom-CatCrySalut.png","1324":"custom-catcrythumbsup.png","1325":"custom-cathammerbonk.png","1326":"custom-catsip.png","1327":"custom-CB_run_laugh.png","1328":"custom-CeciliaBlush.png","1329":"custom-CeciliaConfused.png","1330":"custom-CeciliaHappy.png","1331":"custom-CharlossDurr.png","1332":"custom-checkpins.png","1333":"custom-cheems.png","1334":"custom-chickensus.png","1335":"custom-chickystabby.png","1336":"custom-ChopperAngery.png","1337":"custom-ChopperCross.png","1338":"custom-ChopperWhistle.png","1339":"custom-Chopsuey.png","1340":"custom-cielhi.png","1341":"custom-cielnun.png","1342":"custom-cielrage.png","1343":"custom-CobyCry.png","1344":"custom-CondorianoKek.png","1345":"custom-creep.png","1346":"custom-CrocoAshura.png","1347":"custom-CrocoBoy.png","1348":"custom-CrocoClown.png","1349":"custom-CrocoKid.png","1350":"custom-crocokidDistorted.png","1351":"custom-CrocoKidEvenMoreDistorted.png","1352":"custom-CrocoStare.png","1353":"custom-CrocThink.png","1354":"custom-cry.png","1355":"custom-Crydo.png","1356":"custom-cryRose.png","1357":"custom-cryRoseCry.png","1358":"custom-Crystal.png","1359":"custom-cursedtosi.png","1360":"custom-DB_DinkelBerg.png","1361":"custom-DB_DinkelEntiBerg.png","1362":"custom-DB_DinkelVira.png","1363":"custom-DB_EdikBerg.png","1364":"custom-DB_JoBergShi.png","1365":"custom-DB_ShiroBerg.png","1366":"custom-deadinsidestare.png","1367":"custom-derp.png","1368":"custom-derphov.png","1369":"custom-DerpThumbUp.png","1370":"custom-Derpy_HoF.png","1371":"custom-derp_cat_BlackCat.png","1372":"custom-derp_derp2.png","1373":"custom-derp_lurk_1.png","1374":"custom-derp_lurk_2.png","1375":"custom-derp_lurk_3.png","1376":"custom-derp_lurk_4.png","1377":"custom-die.png","1378":"custom-DoffEZ.png","1379":"custom-Doffycorn.png","1380":"custom-Doffylmao.png","1381":"custom-dogebuff.png","1382":"custom-Dogkek.png","1383":"custom-dogwat.png","1384":"custom-dogwave.png","1385":"custom-DragonStare.png","1386":"custom-DurandalAnnoyed.png","1387":"custom-DurandalFlustered.png","1388":"custom-DurandalLurk.png","1389":"custom-DurandalUnamused.png","1390":"custom-Edikberg.png","1391":"custom-eeveecomf.png","1392":"custom-eeveeshy.png","1393":"custom-eh.png","1394":"custom-EinsteinPathetic.png","1395":"custom-EinsteinSip.png","1396":"custom-emergencymeeting.png","1397":"custom-Emoji.png","1398":"custom-emotepoopsnailhahafatsispoopoohe.png","1399":"custom-EnelLUL.png","1400":"custom-EulaNotLikeThis.png","1401":"custom-evilmodiswatching2.png","1402":"custom-evilnou.png","1403":"custom-evilweeb2.png","1404":"custom-evil_hehe.png","1405":"custom-facepalm.png","1406":"custom-facepalmmega.png","1407":"custom-facepalm_facepalm.png","1408":"custom-Face_ChrisWantFreeCandys.png","1409":"custom-Face_DarkyWhat.png","1410":"custom-Face_EdikStare.png","1411":"custom-Face_GaoCreppy.png","1412":"custom-Face_HaviraDrugs.png","1413":"custom-Face_JoshiDeadInside.png","1414":"custom-Face_nEmaiSceptic.png","1415":"custom-Face_OkeJudge.png","1416":"custom-Face_SaliChrisDerp.png","1417":"custom-Face_ViviIceColdStare.png","1418":"custom-FeelsGoodSakura.png","1419":"custom-Fine.png","1420":"custom-fogel.png","1421":"custom-FoxyKek.png","1422":"custom-FranKEKer.png","1423":"custom-FrankEZ.png","1424":"custom-FrankyAAA.png","1425":"custom-FrankyThumbsDown.png","1426":"custom-FrankyThumbsUp.png","1427":"custom-FrankyYes.png","1428":"custom-FriedHegotchumaru.png","1429":"custom-froggybutt.png","1430":"custom-froggywow.png","1431":"custom-fucc.png","1432":"custom-fuccyuu.png","1433":"custom-fuck_atagohide.png","1434":"custom-fuck_fuu.png","1435":"custom-fuck_sakuraburn.png","1436":"custom-FufuFu.png","1437":"custom-FufuPout.png","1438":"custom-FuHuaAngery.png","1439":"custom-FuHuaApprove.png","1440":"custom-FuHuaConcerned.png","1441":"custom-FuHuaDead.png","1442":"custom-FuHuaDerp.png","1443":"custom-FuHuaDistressed.png","1444":"custom-FuHuaFckYou.png","1445":"custom-FuHuaFlex.png","1446":"custom-FuHuaHappy.png","1447":"custom-FuHuaPat.png","1448":"custom-FuHuaSaltBabe.png","1449":"custom-FuHuaSip.png","1450":"custom-FuHuaSmug.png","1451":"custom-FuHuaWaiting.png","1452":"custom-FujiKEK.png","1453":"custom-FujiLUL.png","1454":"custom-FujiPoint.png","1455":"custom-FujiWoke.png","1456":"custom-fukyou.png","1457":"custom-fuuuuu.png","1458":"custom-Fuwait.png","1459":"custom-ganyu_derp.png","1460":"custom-ganyu_sparkle.png","1461":"custom-Garpathetic.png","1462":"custom-GarPepe.png","1463":"custom-GinCry.png","1464":"custom-Goda.png","1465":"custom-hahamonster.png","1466":"custom-HakiFist.png","1467":"custom-HappyBeard.png","1468":"custom-HappyPantsu.png","1469":"custom-happy_Eeveecompf.png","1470":"custom-havitroll.png","1471":"custom-HawkinsL.png","1472":"custom-Headpat_Holo.png","1473":"custom-heyhey.png","1474":"custom-HI3_Agony.png","1475":"custom-HI3_Forbidden.png","1476":"custom-HI3_Nirvana.png","1477":"custom-HI3_RedLotus.png","1478":"custom-HI3_Sinful.png","1479":"custom-hidethepain.png","1480":"custom-HigoDumb.png","1481":"custom-HigoHappy.png","1482":"custom-HigoIDK.png","1483":"custom-HigoPing.png","1484":"custom-HigoPog.png","1485":"custom-HigoPuppyEyes.png","1486":"custom-HigoSeriously.png","1487":"custom-HigoThink.png","1488":"custom-Higurashiko.png","1489":"custom-HimekoAngery.png","1490":"custom-HimekoDead.png","1491":"custom-HimekoKiss.png","1492":"custom-HimekoLMAO.png","1493":"custom-HimekoMad.png","1494":"custom-HimekoSauced.png","1495":"custom-HimekoSmug.png","1496":"custom-HimekoWTF.png","1497":"custom-Himitsu_kekw.png","1498":"custom-Himitsu_wat.png","1499":"custom-himi_omegalilwoo.png","1500":"custom-Hivivis_Pantsu.png","1501":"custom-hmmm.png","1502":"custom-hmmmm.png","1503":"custom-hmm_TeslaThink.png","1504":"custom-HoEOuch.png","1505":"custom-hornyblushKurumiLewd.png","1506":"custom-horny_blush_aiswallow.png","1507":"custom-HoROK.png","1508":"custom-HoRLurk.png","1509":"custom-HoRSmile.png","1510":"custom-HoSDisgust.png","1511":"custom-HoSWhat.png","1512":"custom-HoSYatta.png","1513":"custom-HoS_funny.png","1514":"custom-HoS_sip.png","1515":"custom-HoT_Cry.png","1516":"custom-HoVChill.png","1517":"custom-HoVCookie.png","1518":"custom-HoVLoading.png","1519":"custom-HoVREEE.png","1520":"custom-HoVSip.png","1521":"custom-HoVSmirk.png","1522":"custom-HoVSmug.png","1523":"custom-HoVSnap.png","1524":"custom-HoVSugoi.png","1525":"custom-HoVWhat.png","1526":"custom-HoVWink.png","1527":"custom-HuaSleep.png","1528":"custom-huehehe.png","1529":"custom-hue_huehue.png","1530":"custom-huhwhat.png","1531":"custom-idk.png","1532":"custom-inspect.png","1533":"custom-isee_isee.png","1534":"custom-Itto_bonk.png","1535":"custom-JahyDisgust.png","1536":"custom-jalter_laugh.png","1537":"custom-jalter_smug.png","1538":"custom-jeannegotem.png","1539":"custom-jeannelurk.png","1540":"custom-Jinbait.png","1541":"custom-JinbeDrive.png","1542":"custom-JinbeiThug.png","1543":"custom-JinBruh.png","1544":"custom-KaidoREEEEEE.png","1545":"custom-KaidoSuccessBreedsJealousy.png","1546":"custom-KallenAmagad.png","1547":"custom-KallenBaka.png","1548":"custom-KallenEvil.png","1549":"custom-KallenGoodJob.png","1550":"custom-KallenWink.png","1551":"custom-KallenWTF.png","1552":"custom-kannahasseensomeshit.png","1553":"custom-kannajail.png","1554":"custom-kannawat.png","1555":"custom-kappa.png","1556":"custom-KappaPog.png","1557":"custom-KasumiBruh.png","1558":"custom-KasumiSurprised.png","1559":"custom-KataCozy.png","1560":"custom-KatafiteMe.png","1561":"custom-KatakuriThink.png","1562":"custom-KataLUL.png","1563":"custom-KataOmegaLUL.png","1564":"custom-KazuhaAngry.png","1565":"custom-KazuhaLuv.png","1566":"custom-KazuhaSleppy.png","1567":"custom-KazuhaSparkle.png","1568":"custom-KazuhaWave.png","1569":"custom-KazuhaWhatMe.png","1570":"custom-kek.png","1571":"custom-KekDog.png","1572":"custom-kek_kek.png","1573":"custom-KenobiTaco.png","1574":"custom-KeqingThumbUp.png","1575":"custom-KevinLurk.png","1576":"custom-KianaBat.png","1577":"custom-KianaBeg.png","1578":"custom-KianaBomb.png","1579":"custom-KianaDerp.png","1580":"custom-KianaDerpBat.png","1581":"custom-KianaDrool.png","1582":"custom-KianaDumb.png","1583":"custom-KianaFish.png","1584":"custom-KianaGrin.png","1585":"custom-KianaHuh.png","1586":"custom-KianaHungry.png","1587":"custom-KianaLewd.png","1588":"custom-KianaNotLikeThis.png","1589":"custom-KianaOhayo.png","1590":"custom-kianapants.png","1591":"custom-KianaShrug.png","1592":"custom-KianaSmug.png","1593":"custom-KianaSmug2.png","1594":"custom-KianaSparkle.png","1595":"custom-KianaSpy.png","1596":"custom-KianaSuggestive.png","1597":"custom-KianaSweat.png","1598":"custom-KianaThink.png","1599":"custom-KianaThonk.png","1600":"custom-KianaTunaNom.png","1601":"custom-KianaWave.png","1602":"custom-KianaWink.png","1603":"custom-Kianawoah.png","1604":"custom-KianaWow.png","1605":"custom-KidSquint.png","1606":"custom-KidYes.png","1607":"custom-KikuTriggered.png","1608":"custom-KillerCry.png","1609":"custom-KillerPsycho.png","1610":"custom-KingShrug.png","1611":"custom-KizaruPog.png","1612":"custom-KizaruWut.png","1613":"custom-KizaruYes.png","1614":"custom-kleebomb.png","1615":"custom-KleeLurk.png","1616":"custom-kleeowosmug.png","1617":"custom-Knight_of_Reverse.png","1618":"custom-konoha_cat.png","1619":"custom-koyabotOK.png","1620":"custom-KumaHappy.png","1621":"custom-KumaPause.png","1622":"custom-KurikaraWhat.png","1623":"custom-Kurumi1.png","1624":"custom-KuzanNo.png","1625":"custom-KuzanPoint.png","1626":"custom-KuzanWoke.png","1627":"custom-LawWat.png","1628":"custom-LawWut.png","1629":"custom-lazy.png","1630":"custom-LETSBUGGINGGO.png","1631":"custom-lFeelsDMan.png","1632":"custom-lick.png","1633":"custom-LiliDead.png","1634":"custom-LiliPog.png","1635":"custom-LiliPolice.png","1636":"custom-LiliSip.png","1637":"custom-LiliSleep.png","1638":"custom-LiliSpray.png","1639":"custom-LiliStare.png","1640":"custom-LiliSweat.png","1641":"custom-LiliVodka.png","1642":"custom-lili_hmmm.png","1643":"custom-lol.png","1644":"custom-LolRun.png","1645":"custom-loveee.png","1646":"custom-LuckyRooFat.png","1647":"custom-LuffyDrool.png","1648":"custom-LuffyEw.png","1649":"custom-LuffyHm.png","1650":"custom-LuffyHuh.png","1651":"custom-LuffyLUL.png","1652":"custom-LuffyMEAT.png","1653":"custom-LuffyNO.png","1654":"custom-LuffyNose.png","1655":"custom-LuffyPog.png","1656":"custom-LuffyThink.png","1657":"custom-LuffyThug.png","1658":"custom-LuffyTruthful.png","1659":"custom-LuffyWave.png","1660":"custom-LuffyZzz.png","1661":"custom-LuigiNut.png","1662":"custom-Luke_Wurstwalker.png","1663":"custom-LUL.png","1664":"custom-lurk.png","1665":"custom-luv_ShiroLuv.png","1666":"custom-MajimaLurk.png","1667":"custom-mamama.png","1668":"custom-mancreepysmile.png","1669":"custom-mariofu.png","1670":"custom-mcheart.png","1671":"custom-meguminlewd.png","1672":"custom-meguminsmug.png","1673":"custom-MeiBlush.png","1674":"custom-MeiCheer.png","1675":"custom-MeiDerp.png","1676":"custom-MeiHappy.png","1677":"custom-MeiJojo.png","1678":"custom-meisip.png","1679":"custom-MeiStare.png","1680":"custom-MeiTantrum.png","1681":"custom-mei_stab.png","1682":"custom-menacing.png","1683":"custom-menherablush.png","1684":"custom-MenheraChan_devil.png","1685":"custom-menheralurk.png","1686":"custom-merchedesGun.png","1687":"custom-MihawkBruh.png","1688":"custom-MimiKussiBussi.png","1689":"custom-Mmmsopp.png","1690":"custom-mock_sponge_mocksponge.png","1691":"custom-mod_is_watching.png","1692":"custom-MomoCreep.png","1693":"custom-MomoNotLikeThis.png","1694":"custom-MonaHeHe.png","1695":"custom-Mondjagt_Amulett.png","1696":"custom-moneyforwhaling.png","1697":"custom-MorgansPing.png","1698":"custom-MoriaDisgust.png","1699":"custom-MoriaFeels.png","1700":"custom-MoriaPepega.png","1701":"custom-MoriaSus.png","1702":"custom-MoriaWide.png","1703":"custom-Mudrock_luv.png","1704":"custom-NamiFlush.png","1705":"custom-NamiGrin.png","1706":"custom-NamiMoney.png","1707":"custom-NamiPinged.png","1708":"custom-NamiPray.png","1709":"custom-NamiWink.png","1710":"custom-NamiWut.png","1711":"custom-naruhodo.png","1712":"custom-nekothonk.png","1713":"custom-nervousdoggo.png","1714":"custom-nicebreath.png","1715":"custom-nicedone.png","1716":"custom-nice_notbad.png","1717":"custom-nice_perfection.png","1718":"custom-nosebleed.png","1719":"custom-notbad.png","1720":"custom-nothanks_nty2.png","1721":"custom-noticeme.png","1722":"custom-NotLikeAtago.png","1723":"custom-notlike_HuTao.png","1724":"custom-notwhale.png","1725":"custom-Nuwaruuun.png","1726":"custom-NuwaVomit.png","1727":"custom-NuwaXD.png","1728":"custom-OdaHaa.png","1729":"custom-OdaIsAHack.png","1730":"custom-odapls.png","1731":"custom-OdenDisgust.png","1732":"custom-okay.png","1733":"custom-OkikuGasp.png","1734":"custom-omegalilwoo.png","1735":"custom-oops.png","1736":"custom-OrochiScheme.png","1737":"custom-OtamaHandsUp.png","1738":"custom-OtamaLurk.png","1739":"custom-OTamaThink.png","1740":"custom-OttoBestGril.png","1741":"custom-OttoScared.png","1742":"custom-OttoThink.png","1743":"custom-ouch.png","1744":"custom-paimondedicated.png","1745":"custom-paimoneat.png","1746":"custom-Paimonflipflop.png","1747":"custom-paimongermon.png","1748":"custom-paimonhehe.png","1749":"custom-PaimonSmugs.png","1750":"custom-paimonstabby.png","1751":"custom-paimonwat.png","1752":"custom-paimonwoke.png","1753":"custom-panic_zelel.png","1754":"custom-panik.png","1755":"custom-Pantsu_Detective.png","1756":"custom-Patrick_Handshake.png","1757":"custom-pat_blush_JavPat.png","1758":"custom-pat_pat.png","1759":"custom-pat_whale_patwhale.png","1760":"custom-PedroPalm.png","1761":"custom-Pen_isCat.png","1762":"custom-pepechrist.png","1763":"custom-pepeCoffee.png","1764":"custom-PepegaLuffy.png","1765":"custom-pepegun.png","1766":"custom-PepeNotes.png","1767":"custom-pepepantsu.png","1768":"custom-pepepog.png","1769":"custom-pepesimp.png","1770":"custom-Pepesleep.png","1771":"custom-Pepe_Comfy.png","1772":"custom-pepe_pantsu_sniff.png","1773":"custom-perfection.png","1774":"custom-PeronaLurk.png","1775":"custom-pikaWTH.png","1776":"custom-pingangry.png","1777":"custom-pog1.png","1778":"custom-PopcornKEK.png","1779":"custom-pout_Laaaaaame_ohcmon.png","1780":"custom-pout_sadpotato.png","1781":"custom-Primogem.png","1782":"custom-PuddingO.png","1783":"custom-PuddingPout.png","1784":"custom-PuddingWink.png","1785":"custom-QiqiLurk.png","1786":"custom-QueenKEKW.png","1787":"custom-QueenREEEEEE.png","1788":"custom-QueenWhat.png","1789":"custom-rabwhat.png","1790":"custom-RainbowCard.png","1791":"custom-RankoCry.png","1792":"custom-RankoHype.png","1793":"custom-Rankopout.png","1794":"custom-RankoSmile.png","1795":"custom-RateUpIsALie.png","1796":"custom-RayCringe.png","1797":"custom-RaySmart.png","1798":"custom-ready_set_lewd.png","1799":"custom-really.png","1800":"custom-remsmile.png","1801":"custom-RIP_HoR.png","1802":"custom-rip_horF.png","1803":"custom-RitaAngry.png","1804":"custom-RitaAraAra.png","1805":"custom-RitaBlush.png","1806":"custom-RitaCheer.png","1807":"custom-RitaChuu.png","1808":"custom-RitaFlustered.png","1809":"custom-ritaknife.png","1810":"custom-RitaLove.png","1811":"custom-RitaPout.png","1812":"custom-RitaSip.png","1813":"custom-RitaSmile.png","1814":"custom-RitaSurprised.png","1815":"custom-RobinChuckle.png","1816":"custom-RobinHUH.png","1817":"custom-RobinSmug.png","1818":"custom-RogerFinger.png","1819":"custom-RogerLaugh.png","1820":"custom-roondarkLurk.png","1821":"custom-RosemaryCry.png","1822":"custom-rossmariecry.png","1823":"custom-RoyalFlush.png","1824":"custom-RozaDead.png","1825":"custom-RozaHi.png","1826":"custom-RozaNotLikeThis.png","1827":"custom-RozaOops.png","1828":"custom-RozaLurk.png","1829":"custom-RozaPolice.png","1830":"custom-RozaPout.png","1831":"custom-RozaReee.png","1832":"custom-RozaScout.png","1833":"custom-RozaSprayed.png","1834":"custom-RozaTantrum.png","1835":"custom-RozaThink.png","1836":"custom-RozaWeird.png","1837":"custom-RozaYeet.png","1838":"custom-russian_cabbage.png","1839":"custom-SaboEvil.png","1840":"custom-SaboThumbsUp.png","1841":"custom-SadHoshi.png","1842":"custom-SakuraBan.png","1843":"custom-SakuraBomb.png","1844":"custom-SakuraBox.png","1845":"custom-SakuraBully.png","1846":"custom-SakuraCool.png","1847":"custom-SakuraDab.png","1848":"custom-SakuraDerp.png","1849":"custom-SakuraHuehue.png","1850":"custom-SakuraHurt.png","1851":"custom-SakuraKick.png","1852":"custom-SakuraLewd.png","1853":"custom-SakuraLuv.png","1854":"custom-SakuraCry.png","1855":"custom-SakuraWonder.png","1856":"custom-SakuraWTF.png","1857":"custom-Salty_kitty.png","1858":"custom-SanjiCreep.png","1859":"custom-SanjiDab.png","1860":"custom-SanjiHollow.png","1861":"custom-SanjiL.png","1862":"custom-Sanjimmhmmm.png","1863":"custom-SanjiSimp.png","1864":"custom-SanjiSmart.png","1865":"custom-SanjiSmoke.png","1866":"custom-SanjiSneak.png","1867":"custom-SanjiWK.png","1868":"custom-SanjiWut.png","1869":"custom-SanjiYesHoney.png","1870":"custom-SanruiStare.png","1871":"custom-sbs.png","1872":"custom-SeeleAra.png","1873":"custom-seelecry.png","1874":"custom-SeeleDead1.png","1875":"custom-SeeleDead2.png","1876":"custom-seelederp.png","1877":"custom-SeeleDisgust.png","1878":"custom-SeeleLurk.png","1879":"custom-SeeleMad.png","1880":"custom-SeeleNervous.png","1881":"custom-SeelePat.png","1882":"custom-SeelePout.png","1883":"custom-SeeleSmile.png","1884":"custom-SeeleSmile2.png","1885":"custom-SeeleStalk.png","1886":"custom-SeeleStare.png","1887":"custom-SeeleSweat.png","1888":"custom-seeleyan.png","1889":"custom-SeeleYandere.png","1890":"custom-seele_heart.png","1891":"custom-SeluneLurk.png","1892":"custom-SeluneYandere.png","1893":"custom-SengokuHmm2.png","1894":"custom-SengokuPalm.png","1895":"custom-ShanksEvil.png","1896":"custom-ShanksHmmm.png","1897":"custom-ShanksTroll.png","1898":"custom-ShanksYes.png","1899":"custom-Shilikek.png","1900":"custom-shrugidk.png","1901":"custom-shut.png","1902":"custom-shy.png","1903":"custom-SiegfriedAnnoyed.png","1904":"custom-SiegfriedDante.png","1905":"custom-SiegfriedGotchu.png","1906":"custom-SiegfriedHelpMe.png","1907":"custom-SiegfriedLewd.png","1908":"custom-SiegfriedSugoi.png","1909":"custom-simp_card.png","1910":"custom-Simp_sauce.png","1911":"custom-SinEvilLaugh.png","1912":"custom-SinStare.png","1913":"custom-SirinConcern.png","1914":"custom-SirinGhost.png","1915":"custom-SirinHappeh.png","1916":"custom-SirinPat.png","1917":"custom-SirinPout.png","1918":"custom-SirinSmile.png","1919":"custom-SirinSmug.png","1920":"custom-SirinSurprised.png","1921":"custom-skadi_fallen.png","1922":"custom-sleepymorning.png","1923":"custom-smoll.png","1924":"custom-smolteriderp.png","1925":"custom-smug.png","1926":"custom-smugmotep.png","1927":"custom-spongedisgust.png","1928":"custom-spongefish.png","1929":"custom-spongemhm.png","1930":"custom-SpongeSadWaiting.png","1931":"custom-spongespongepray.png","1932":"custom-spongeWTF.png","1933":"custom-SpongeYeees.png","1934":"custom-sponge_hue_spongefish.png","1935":"custom-StanAnnoyed.png","1936":"custom-StigBot.png","1937":"custom-stigTop.png","1938":"custom-sucrosefbi.png","1939":"custom-sucroseOK.png","1940":"custom-sugoi.png","1941":"custom-Suicide.png","1942":"custom-super_F.png","1943":"custom-sus_searchmode.png","1944":"custom-sweat.png","1945":"custom-TamaHuh.png","1946":"custom-TamaWot.png","1947":"custom-TanakaPog.png","1948":"custom-tayronMoewe.png","1949":"custom-TenOutOfTen.png","1950":"custom-TeReeRee.png","1951":"custom-teri.png","1952":"custom-teriawaken.png","1953":"custom-TeriBleed.png","1954":"custom-TeriCelebrate.png","1955":"custom-TeriCheers.png","1956":"custom-TeriChrist.png","1957":"custom-TeriCool.png","1958":"custom-tericry.png","1959":"custom-TeriCube.png","1960":"custom-teriderp.png","1961":"custom-TeriDerp1.png","1962":"custom-teriderpjuicy.png","1963":"custom-TeriDerpMelon.png","1964":"custom-TeriDorime.png","1965":"custom-Teriehe.png","1966":"custom-TeriFied.png","1967":"custom-TeriHuehue.png","1968":"custom-TeriMiffed.png","1969":"custom-TeriPoint.png","1970":"custom-TeriRip.png","1971":"custom-TeRiRiSleepy.png","1972":"custom-TeriCry.png","1973":"custom-TeriScaredLurk.png","1974":"custom-TeriSmoke.png","1975":"custom-TeriSparkle.png","1976":"custom-TeriSugoi.png","1977":"custom-TeriSurprised.png","1978":"custom-TeriTeehee.png","1979":"custom-TeriTeri.png","1980":"custom-TeriThink.png","1981":"custom-TeriTthink.png","1982":"custom-TeriWave.png","1983":"custom-TeriWhat.png","1984":"custom-teriwow.png","1985":"custom-TeslaThink.png","1986":"custom-tf1.png","1987":"custom-tf2.png","1988":"custom-tf3.png","1989":"custom-tf4.png","1990":"custom-tf5.png","1991":"custom-thanks_blush.png","1992":"custom-thanks_cat_blush_catblush.png","1993":"custom-thanks_cheers.png","1994":"custom-thinkderp.png","1995":"custom-Thinkenobi.png","1996":"custom-thinkhmm.png","1997":"custom-thumbsup.png","1998":"custom-tohruhasseensomeshit.png","1999":"custom-TohruSmug.png","2000":"custom-tosimachtauge.png","2001":"custom-Trashigi.png","2002":"custom-trg.png","2003":"custom-tutel.png","2004":"custom-TyrannUwU.png","2005":"custom-ugh.png","2006":"custom-uhmwat.png","2007":"custom-UltiPoint.png","2008":"custom-UltiWhy.png","2009":"custom-UniFlex.png","2010":"custom-UrougeFedora.png","2011":"custom-Uso.png","2012":"custom-UsoCross.png","2013":"custom-UsoNegative.png","2014":"custom-UsoppBan.png","2015":"custom-UsoppDisgust.png","2016":"custom-UsopPepega.png","2017":"custom-UsoppHuh.png","2018":"custom-UsoppLmfao.png","2019":"custom-UsoppLurk.png","2020":"custom-UsoppSus.png","2021":"custom-Vasco.png","2022":"custom-VelionaAngry.png","2023":"custom-VelionaDerp.png","2024":"custom-VelionaMwaha.png","2025":"custom-VelionaWicked.png","2026":"custom-veliSparkle.png","2027":"custom-veliStare.png","2028":"custom-ViviChuckle.png","2029":"custom-ViviPanic.png","2030":"custom-VodkaBox.png","2031":"custom-VodkaHug.png","2032":"custom-vorbildlich.png","2033":"custom-vorzueglich.png","2034":"custom-WapolHouse.png","2035":"custom-WapolTriggered.png","2036":"custom-wat.png","2037":"custom-WBDisgust.png","2038":"custom-WBWhat.png","2039":"custom-weirdangry.png","2040":"custom-WelCum.png","2041":"custom-WeltApathetic.png","2042":"custom-WeltHmph.png","2043":"custom-WeltLol.png","2044":"custom-whale.png","2045":"custom-what.png","2046":"custom-what_dog_nervous.png","2047":"custom-what_hob_hobtrg.png","2048":"custom-what_hrld.png","2049":"custom-what_hrld2.png","2050":"custom-what_oops_oops1.png","2051":"custom-what_oops_oops2.png","2052":"custom-what_pika_wthpika.png","2053":"custom-what_sus_pika_wthpika.png","2054":"custom-what_wat2.png","2055":"custom-what_wat3.png","2056":"custom-what_wth.png","2057":"custom-what_wth2.png","2058":"custom-what_wth2_tosi.png","2059":"custom-what_wthrabbit.png","2060":"custom-what__paimon_Paimonflipflop.png","2061":"custom-wooow.png","2062":"custom-wow_cute_Kianawoah.png","2063":"custom-wtf.png","2064":"custom-wtfc2.png","2065":"custom-wth.png","2066":"custom-wth2.png","2067":"custom-wthrabbit.png","2068":"custom-XDoubt.png","2069":"custom-yaelul.png","2070":"custom-yaenosebleed.png","2071":"custom-YamatoAngry.png","2072":"custom-YamatoHappy.png","2073":"custom-YamatoShy.png","2074":"custom-youtried.png","2075":"custom-yufka.png","2076":"custom-zerotwolaugh.png","2077":"custom-zerotwoluv.png","2078":"custom-ZeroTwoLuv1.png","2079":"custom-zerotwopout.png","2080":"custom-ZeusMonka.png","2081":"custom-ZeusShit.png","2082":"custom-ZombieNotImpressed.png","2083":"custom-ZoroCope.png","2084":"custom-ZoroGrief.png","2085":"custom-ZoroL.png","2086":"custom-ZoroNothing.png","2087":"custom-ZoroNut.png","2088":"custom-ZoroLurk.png","2089":"custom-ZoroWeary.png","2090":"custom-zzzoro.png"}
